arklex/__init__.py
arklex/memory/core.py
arklex/memory/prompts.py
arklex/memory/entities/memory_entities.py
arklex/memory/test/teststm.py
arklex/models/embedding_config.py
arklex/models/llm_config.py
arklex/models/model_service.py
arklex/orchestrator/orchestrator.py
arklex/orchestrator/entities/orchestrator_param_entities.py
arklex/orchestrator/entities/orchestrator_state_entities.py
arklex/orchestrator/entities/taskgraph_entities.py
arklex/orchestrator/executor/entities.py
arklex/orchestrator/executor/executor.py
arklex/orchestrator/generator/README.md
arklex/orchestrator/generator/__init__.py
arklex/orchestrator/generator/generator.py
arklex/orchestrator/generator/prompts.py
arklex/orchestrator/generator/core/__init__.py
arklex/orchestrator/generator/core/generator.py
arklex/orchestrator/generator/docs/__init__.py
arklex/orchestrator/generator/docs/document_loader.py
arklex/orchestrator/generator/docs/document_processor.py
arklex/orchestrator/generator/docs/document_validator.py
arklex/orchestrator/generator/formatting/__init__.py
arklex/orchestrator/generator/formatting/edge_formatter.py
arklex/orchestrator/generator/formatting/graph_validator.py
arklex/orchestrator/generator/formatting/node_formatter.py
arklex/orchestrator/generator/formatting/task_graph_formatter.py
arklex/orchestrator/generator/tasks/__init__.py
arklex/orchestrator/generator/tasks/best_practice_manager.py
arklex/orchestrator/generator/tasks/reusable_task_manager.py
arklex/orchestrator/generator/tasks/task_generator.py
arklex/orchestrator/generator/ui/__init__.py
arklex/orchestrator/generator/ui/data_manager.py
arklex/orchestrator/generator/ui/input_modal.py
arklex/orchestrator/generator/ui/protocols.py
arklex/orchestrator/generator/ui/task_editor.py
arklex/orchestrator/nlu/core/intent.py
arklex/orchestrator/nlu/core/slot.py
arklex/orchestrator/nlu/entities/slot_entities.py
arklex/orchestrator/nlu/utils/formatters.py
arklex/orchestrator/task_graph/agent_graph.py
arklex-0.1.16.dist-info/METADATA
arklex-0.1.16.dist-info/WHEEL
arklex-0.1.16.dist-info/licenses/LICENSE.md
arklex-0.1.16.dist-info/RECORD
