Metadata-Version: 2.4
Name: arklex
Version: 0.1.16
Summary: The official Python library for the arklex API
Project-URL: Homepage, https://github.com/arklexai/Agent-First-Organization
Project-URL: Issues, https://github.com/arklexai/Agent-First-Organization/issues
Author-email: "Arklex.AI" <support@arklex.ai>
License-Expression: MIT
License-File: LICENSE.md
Classifier: Operating System :: OS Independent
Classifier: Programming Language :: Python :: 3.10
Classifier: Programming Language :: Python :: 3.11
Classifier: Programming Language :: Python :: 3.12
Requires-Python: >=3.10
Requires-Dist: email-validator<3.0.0,>=2.2.0
Requires-Dist: faiss-cpu<2.0.0,>=1.10.0
Requires-Dist: fastapi-cli<1.0.0,>=0.0.5
Requires-Dist: fastapi<1.0.0,>=0.115.3
Requires-Dist: google-generativeai<1.0.0,>=0.8.0
Requires-Dist: greenlet<4.0.0,>=3.1.1
Requires-Dist: httptools<1.0.0,>=0.6.4
Requires-Dist: janus<2.0.0,>=1.0.0
Requires-Dist: jinja2<4.0.0,>=3.1.0
Requires-Dist: langchain-community<1.0.0,>=0.4.0
Requires-Dist: langchain-openai<2.0.0,>=1.0.0
Requires-Dist: linkify-it-py<3.0.0,>=2.0.3
Requires-Dist: markdown>=3.8
Requires-Dist: mdit-py-plugins<1.0.0,>=0.4.2
Requires-Dist: networkx<4.0.0,>=3.4.2
Requires-Dist: openai-agents<1.0.0,>=0.2.10
Requires-Dist: openai<3.0.0,>=1.109.1
Requires-Dist: orjson<4.0.0,>=3.10.1
Requires-Dist: parsedatetime<3.0,>=2.6
Requires-Dist: phonenumbers<9.0.0,>=8.13.48
Requires-Dist: pydantic-ai<1.0.0,>=0.1.10
Requires-Dist: pysocks<2.0.0,>=1.7.1
Requires-Dist: pytest-asyncio<0.19.0,>=0.18.0
Requires-Dist: pytest-cov<4.0.0,>=3.0.0
Requires-Dist: pytest-env<2.0.0,>=1.0.0
Requires-Dist: pytest-mock<4.0.0,>=3.10.0
Requires-Dist: pytest<9.0.0,>=8.3.5
Requires-Dist: python-levenshtein<1.0.0,>=0.26.0
Requires-Dist: python-multipart<1.0.0,>=0.0.12
Requires-Dist: redis<7.0.0,>=6.2.0
Requires-Dist: rich<15.0.0,>=14.0.0
Requires-Dist: scikit-learn<2.0.0,>=1.7.0
Requires-Dist: selenium<5.0.0,>=4.26.1
Requires-Dist: tavily-python<1.0.0,>=0.5.0
Requires-Dist: textual<1.0.0,>=0.85.2
Requires-Dist: typing-extensions<5.0.0,>=4.13.2
Requires-Dist: undecorated>=0.3.0
Requires-Dist: unstructured-client<1.0.0,>=0.30.0
Requires-Dist: unstructured[doc,docx,md,ppt,pptx,xlsx]<1.0.0,>=0.16.4
Requires-Dist: watchfiles<1.0.0,>=0.24.0
Requires-Dist: webdriver-manager==4.0.2
Requires-Dist: websockets<16.0,>=14.0
Provides-Extra: faiss
Requires-Dist: sentence-transformers<3.0.0,>=2.2.2; extra == 'faiss'
Provides-Extra: hubspot
Requires-Dist: hubspot-api-client<12.0.0,>=11.1.0; extra == 'hubspot'
Provides-Extra: llm
Requires-Dist: langchain-anthropic<2.0.0,>=0.3.5; extra == 'llm'
Requires-Dist: langchain-google-genai<3.0.0,>=2.0.9; extra == 'llm'
Requires-Dist: langchain-huggingface<2.0.0,>=0.3.0; extra == 'llm'
Provides-Extra: milvus
Requires-Dist: mysql-connector-python<9.0.0,>=8.3.0; extra == 'milvus'
Requires-Dist: pymilvus<3.0.0,>=2.4.7; extra == 'milvus'
Provides-Extra: shopify
Requires-Dist: shopifyapi<13.0.0,>=12.7.0; extra == 'shopify'
Provides-Extra: strict-versions
Requires-Dist: email-validator==2.2.0; extra == 'strict-versions'
Requires-Dist: faiss-cpu==1.13.2; extra == 'strict-versions'
Requires-Dist: fastapi-cli==0.0.5; extra == 'strict-versions'
Requires-Dist: fastapi==0.116.1; extra == 'strict-versions'
Requires-Dist: google-generativeai==0.8.0; extra == 'strict-versions'
Requires-Dist: greenlet==3.1.1; extra == 'strict-versions'
Requires-Dist: httptools==0.6.4; extra == 'strict-versions'
Requires-Dist: hubspot-api-client==11.1.0; extra == 'strict-versions'
Requires-Dist: janus==1.0.0; extra == 'strict-versions'
Requires-Dist: jinja2==3.1.4; extra == 'strict-versions'
Requires-Dist: langchain-community==0.4.1; extra == 'strict-versions'
Requires-Dist: langchain-openai==1.0.1; extra == 'strict-versions'
Requires-Dist: linkify-it-py==2.0.3; extra == 'strict-versions'
Requires-Dist: markdown==3.8; extra == 'strict-versions'
Requires-Dist: mdit-py-plugins==0.4.2; extra == 'strict-versions'
Requires-Dist: mysql-connector-python==8.3.0; extra == 'strict-versions'
Requires-Dist: networkx==3.4.2; extra == 'strict-versions'
Requires-Dist: openai-agents==0.2.10; extra == 'strict-versions'
Requires-Dist: openai==1.109.1; extra == 'strict-versions'
Requires-Dist: orjson==3.11.1; extra == 'strict-versions'
Requires-Dist: parsedatetime==2.6; extra == 'strict-versions'
Requires-Dist: phonenumbers==8.13.48; extra == 'strict-versions'
Requires-Dist: pydantic-ai==0.1.10; extra == 'strict-versions'
Requires-Dist: pymilvus==2.4.7; extra == 'strict-versions'
Requires-Dist: pysocks==1.7.1; extra == 'strict-versions'
Requires-Dist: pytest-asyncio==0.18.0; extra == 'strict-versions'
Requires-Dist: pytest-cov==3.0.0; extra == 'strict-versions'
Requires-Dist: pytest-env==1.0.0; extra == 'strict-versions'
Requires-Dist: pytest-mock==3.10.0; extra == 'strict-versions'
Requires-Dist: pytest==8.3.5; extra == 'strict-versions'
Requires-Dist: python-levenshtein==0.26.0; extra == 'strict-versions'
Requires-Dist: python-multipart==0.0.12; extra == 'strict-versions'
Requires-Dist: redis==6.2.0; extra == 'strict-versions'
Requires-Dist: selenium==4.26.1; extra == 'strict-versions'
Requires-Dist: shopifyapi==12.7.0; extra == 'strict-versions'
Requires-Dist: tavily-python==0.5.0; extra == 'strict-versions'
Requires-Dist: textual==0.85.2; extra == 'strict-versions'
Requires-Dist: twilio==9.4.1; extra == 'strict-versions'
Requires-Dist: undecorated==0.3.0; extra == 'strict-versions'
Requires-Dist: unstructured-client==0.30.0; extra == 'strict-versions'
Requires-Dist: unstructured[doc,docx,md,ppt,pptx,xlsx]==0.16.4; extra == 'strict-versions'
Requires-Dist: watchfiles==0.24.0; extra == 'strict-versions'
Requires-Dist: webdriver-manager==4.0.2; extra == 'strict-versions'
Provides-Extra: twilio
Requires-Dist: twilio<10.0.0,>=9.4.1; extra == 'twilio'
